{"name":null,"assets":"aoy4:pathy42:assets%2Fweek1%2Fimages%2Fpoly%2Fbgday.pngy4:sizei100568y4:typey5:IMAGEy2:idR1y7:preloadtgoR0y45:assets%2Fweek1%2Fimages%2Fpoly%2Fbglights.pngR2i410656R3R4R5R7R6tgoR0y46:assets%2Fweek1%2Fimages%2Fpoly%2Fbgmorning.pngR2i90366R3R4R5R8R6tgoR0y44:assets%2Fweek1%2Fimages%2Fpoly%2Fbgnight.pngR2i93195R3R4R5R9R6tgoR0y49:assets%2Fweek1%2Fimages%2Fpoly%2FpolyDialogue.pngR2i165094R3R4R5R10R6tgoR0y49:assets%2Fweek1%2Fimages%2Fpoly%2FpolyDialogue.xmlR2i1116R3y4:TEXTR5R11R6tgoR0y48:assets%2Fweek1%2Fimages%2Fpoly%2Fpoly_assets.pngR2i2251707R3R4R5R13R6tgoR0y48:assets%2Fweek1%2Fimages%2Fpoly%2Fpoly_assets.xmlR2i17062R3R12R5R14R6tgoR0y49:assets%2Fweek1%2Fimages%2Fpoly_bubble_talking.pngR2i146222R3R4R5R15R6tgoR0y49:assets%2Fweek1%2Fimages%2Fpoly_bubble_talking.xmlR2i4892R3R12R5R16R6tgh","rootPath":"../","version":2,"libraryArgs":[],"libraryType":null}